regdiffusion/__init__.py
regdiffusion/cli.py
regdiffusion/evaluator.py
regdiffusion/grn.py
regdiffusion/logger.py
regdiffusion/trainer.py
regdiffusion/data/__init__.py
regdiffusion/data/beeline.py
regdiffusion/data/microglia.py
regdiffusion/data/utils.py
regdiffusion/models/__init__.py
regdiffusion/models/regdiffusion.py
regdiffusion/plot/__init__.py
regdiffusion/plot/pyvis.py
regdiffusion-0.1.0.dist-info/entry_points.txt
regdiffusion-0.1.0.dist-info/licenses/LICENSE
regdiffusion-0.1.0.dist-info/WHEEL
regdiffusion-0.1.0.dist-info/METADATA
regdiffusion-0.1.0.dist-info/RECORD
