Metadata-Version: 2.4
Name: regdiffusion
Version: 0.1.0
Summary: Gene Regulatory Networks Inference using diffusion model
Author-email: Hao Zhu <haozhu233@gmail.com>, Donna Slonim <donna.slonim@tufts.edu>
Maintainer-email: Hao Zhu <haozhu233@gmail.com>
Classifier: License :: OSI Approved :: Apache Software License
License-File: LICENSE
Requires-Dist: numpy>=1.16.5
Requires-Dist: pandas>=1.1.1
Requires-Dist: torch
Requires-Dist: tqdm
Requires-Dist: scanpy
Requires-Dist: scikit-learn
Requires-Dist: h5py
Requires-Dist: pyvis
Project-URL: Home, https://github.com/TuftsBCB/RegDiffusion
